{"name":"2e4e0fe0-6b89-44e0-86fd-56f282d38d26","id":"/providers/Microsoft.Flow/flows/2e4e0fe0-6b89-44e0-86fd-56f282d38d26","type":"Microsoft.Flow/flows","properties":{"apiId":"/providers/Microsoft.PowerApps/apis/shared_logicflows","displayName":"approvbHistory","definition":{"metadata":{"workflowEntityId":null,"processAdvisorMetadata":null,"flowChargedByPaygo":null,"flowclientsuspensionreason":"None","flowclientsuspensiontime":null,"flowclientsuspensionreasondetails":null,"creator":{"id":"5e721040-82be-41f0-b815-e35446b653bc","type":"User","tenantId":"6e394566-a548-40b4-b5eb-608fe9eb653b"},"provisioningMethod":"FromDefinition","failureAlertSubscription":true,"clientLastModifiedTime":"2023-07-18T10:00:28.8194235Z"},"$schema":"https://schema.management.azure.com/providers/Microsoft.Logic/schemas/2016-06-01/workflowdefinition.json#","contentVersion":"1.0.0.0","parameters":{"$connections":{"defaultValue":{},"type":"Object"},"$authentication":{"defaultValue":{},"type":"SecureObject"}},"triggers":{"manual":{"metadata":{"operationMetadataId":"fa380092-fe63-43c7-82d9-9a5dfb1deae9"},"type":"Request","kind":"PowerApp","inputs":{"schema":{"type":"object","properties":{"Getitem_Id":{"type":"integer","format":"int64","description":"Unique identifier of item to be retrieved","x-ms-powerflows-param-ispartial":false}},"required":["Getitem_Id"]}}}},"actions":{"Get_item":{"runAfter":{},"metadata":{"operationMetadataId":"efa68436-d2a6-45fd-be88-6fd1708bd292"},"type":"OpenApiConnection","inputs":{"host":{"apiId":"/providers/Microsoft.PowerApps/apis/shared_sharepointonline","connectionName":"shared_sharepointonline","operationId":"GetItem"},"parameters":{"dataset":"https://nl53.sharepoint.com/sites/EditForm","table":"53a5392d-b261-468d-80af-3d1be8246f36","id":"@triggerBody()['Getitem_Id']"},"authentication":{"value":"@json(decodeBase64(triggerOutputs().headers['X-MS-APIM-Tokens']))['$ConnectionKey']","type":"Raw"}}},"Update_item":{"runAfter":{"Get_item":["Succeeded"]},"metadata":{"operationMetadataId":"25972d63-be17-4991-b7e0-146a0ccd9f36"},"type":"OpenApiConnection","inputs":{"host":{"apiId":"/providers/Microsoft.PowerApps/apis/shared_sharepointonline","connectionName":"shared_sharepointonline","operationId":"PatchItem"},"parameters":{"dataset":"https://nl53.sharepoint.com/sites/EditForm","table":"af015d63-fe89-4f22-8f45-1e0955822f2a","id":"@outputs('Get_item')?['body/Title2']","item/Title":"@{outputs('Get_item')?['body/Created']}, @{outputs('Get_item')?['body/EmployeeName']}","item/Approver/Claims":"i:0#.f|membership|alexw@nl53.onmicrosoft.com","item/ActionByApprover/Value":"Approved","item/Comments":"@outputs('Get_item')?['body/Comments']"},"authentication":{"value":"@json(decodeBase64(triggerOutputs().headers['X-MS-APIM-Tokens']))['$ConnectionKey']","type":"Raw"}}}}},"connectionReferences":{"shared_sharepointonline":{"connectionName":"c96e609550284677b6837f405bd7a9e3","source":"Invoker","id":"/providers/Microsoft.PowerApps/apis/shared_sharepointonline","tier":"NotSpecified"}},"flowFailureAlertSubscribed":false,"isManaged":false}}